Workbook

Sheet Title Page
B2: This spreadsheet supports STUDENT analysis of the case “Horniman Horticulture” (UVA-F-1512).
A4: This spreadsheet was prepared by Michael J. Schill, Professor of Business Administration. Copyright © 2011 by the University of Virginia Darden School Foundation, Charlottesville, VA. All rights reserved. For customer service inquiries, send an e-mail to sales@dardenbusinesspublishing.com. No part of this publication may be reproduced, stored in a retrieval system, posted to the Internet, or transmitted in any form or by any means—electronic, mechanical, photocopying, recording, or otherwise—without the permission of the Darden School Foundation.
A5: Rev. Nov. 2, 2016

Sheet Exh 1
A1: Exhibit 1
A2: HORNIMAN HORTICULTURE
A3: Projected Horniman Horticulture Financial Summary (in thousands of dollars)
B6: 2012 | C6: 2013 | D6: 2014 | E6: 2015
A7: Profit and loss statement
A8: Revenue | B8: 788.5 | C8: 807.6 | D8: 908.2 | E8: 1048.8
A9: Cost of goods sold | B9: 402.9 | C9: 428.8 | D9: 437.7 | E9: 503.4
A10: Gross profit | B10: =B8-B9 -> 385.6 | C10: =C8-C9 -> 378.8 | D10: =D8-D9 -> 470.5 | E10: =E8-E9 -> 545.4
A11: SG&A expense | B11: 301.2 | C11: 302 | D11: 356 | E11: 404.5
A12: Depreciation | B12: 34.2 | C12: 38.4 | D12: 36.3 | E12: 40.9
A13: Operating profit | B13: =B10-B11-B12 -> 50.2 | C13: =C10-C11-C12 -> 38.4 | D13: =D10-D11-D12 -> 78.2 | E13: =E10-E11-E12 -> 100
A14: Taxes | B14: 17.6 | C14: 13.1 | D14: 26.2 | E14: 39.2
A15: Net profit | B15: =B13-B14 -> 32.6 | C15: =C13-C14 -> 25.3 | D15: =D13-D14 -> 52 | E15: =E13-E14 -> 60.8
A17: Balance sheet
A18: Cash | B18: 120.1 | C18: 105.2 | D18: 66.8 | E18: 9.4
A19: Accounts receivable | B19: 90.6 | C19: 99.5 | D19: 119.5 | E19: 146.4
A20: Inventory1 | B20: 468.3 | C20: 507.6 | D20: 523.4 | E20: 656.9
A21: Other current assets2 | B21: 20.9 | C21: 19.3 | D21: 22.6 | E21: 20.9
A22: Current assets | B22: =SUM(B18:B21) -> 699.9 | C22: =SUM(C18:C21) -> 731.6 | D22: =SUM(D18:D21) -> 732.3 | E22: =SUM(E18:E21) -> 833.6
A23: Net fixed assets3 | B23: 332.1 | C23: 332.5 | D23: 384.3 | E23: 347.9
A24: Total assets | B24: =B22+B23 -> 1032 | C24: =C22+C23 -> 1064.1 | D24: =D22+D23 -> 1116.6 | E24: =E22+E23 -> 1181.5
A26: Accounts payable | B26: 6 | C26: 5.3 | D26: 4.5 | E26: 5
A27: Wages payable | B27: 19.7 | C27: 22 | D27: 22.1 | E27: 24.4
A28: Other payables | B28: 10.2 | C28: 15.4 | D28: 16.6 | E28: 17.9
A29: Current liabilities | B29: =SUM(B26:B28) -> 35.9 | C29: =SUM(C26:C28) -> 42.7 | D29: =SUM(D26:D28) -> 43.2 | E29: =SUM(E26:E28) -> 47.3
A30: Net worth | B30: =B24-B29 -> 996.1 | C30: =B30+C15 -> 1021.4 | D30: =C30+D15 -> 1073.4 | E30: =D30+E15 -> 1134.2
A32: Capital expenditure | B32: 22 | C32: 38.8 | D32: 88.1 | E32: 4.5
A33: Purchases4 | B33: 140.8 | C33: 145.2 | D33: 161.2 | E33: 185.1
A35: 1 Inventory investment was valued at the lower of cost or market. The cost of inventory was determined by accumulating the costs associated with preparing the plants for sale. Costs that were typically capitalized as inventory included direct labor, materials (soil, water, containers, stakes, labels, chemicals), scrap, and overhead.
A36: 2 Other current assets included consigned inventory, prepaid expenses, and assets held for sale.
A37: 3 Net fixed assets included land, buildings and improvements, equipment, and software.
A38: 4 Purchases represented the annual amount paid to suppliers.

Sheet Exh 2
A1: Exhibit 2
A2: HORNIMAN HORTICULTURE
A3: Financial Ratio Analysis and Benchmarking
B5: 2012 | C5: 2013 | D5: 2014 | E5: 2015 | G5: Benchmark1
A7: Revenue growth | B7: 0.029 | C7: ='Exh 1'!C8/'Exh 1'!B8-1 -> 0.024223209 | D7: ='Exh 1'!D8/'Exh 1'!C8-1 -> 0.12456662 | E7: ='Exh 1'!E8/'Exh 1'!D8-1 -> 0.15481172 | G7: -0.018
A8: Gross margin (Gross profit / Revenue) | B8: ='Exh 1'!B10/'Exh 1'!B8 -> 0.4890298 | C8: ='Exh 1'!C10/'Exh 1'!C8 -> 0.46904408 | D8: ='Exh 1'!D10/'Exh 1'!D8 -> 0.5180577 | E8: ='Exh 1'!E10/'Exh 1'!E8 -> 0.52002288 | G8: 0.489
A9: Operating margin (Op. profit / Revenue) | B9: ='Exh 1'!B13/'Exh 1'!B8 -> 0.063665187 | C9: ='Exh 1'!C13/'Exh 1'!C8 -> 0.047548291 | D9: ='Exh 1'!D13/'Exh 1'!D8 -> 0.086104382 | E9: ='Exh 1'!E13/'Exh 1'!E8 -> 0.095347063 | G9: 0.076
A10: Net profit margin (Net profit / Revenue) | B10: ='Exh 1'!B15/'Exh 1'!B8 -> 0.041344325 | C10: ='Exh 1'!C15/'Exh 1'!C8 -> 0.03132739 | D10: ='Exh 1'!D15/'Exh 1'!D8 -> 0.057256111 | E10: ='Exh 1'!E15/'Exh 1'!E8 -> 0.057971014 | G10: 0.028
A12: Return on assets (Net profit / Total assets) | B12: ='Exh 1'!B15/'Exh 1'!B24 -> 0.031589147 | C12: ='Exh 1'!C15/'Exh 1'!C24 -> 0.023775961 | D12: ='Exh 1'!D15/'Exh 1'!D24 -> 0.046569944 | E12: ='Exh 1'!E15/'Exh 1'!E24 -> 0.051460008 | G12: 0.029
A13: Return on capital (Net profit / Total capital) | B13: ='Exh 1'!B15/'Exh 1'!B30 -> 0.032727638 | C13: ='Exh 1'!C15/'Exh 1'!C30 -> 0.024769924 | D13: ='Exh 1'!D15/'Exh 1'!D30 -> 0.048444196 | E13: ='Exh 1'!E15/'Exh 1'!E30 -> 0.053606066 | G13: 0.04
A15: Receivable days (AR / Revenue * 365) | B15: ='Exh 1'!B19/'Exh 1'!B8*365 -> 41.939125 | C15: ='Exh 1'!C19/'Exh 1'!C8*365 -> 44.969663 | D15: ='Exh 1'!D19/'Exh 1'!D8*365 -> 48.026316 | E15: ='Exh 1'!E19/'Exh 1'!E8*365 -> 50.949657 | G15: 21.8
A16: Inventory days (Inventory / COGS * 365) | B16: ='Exh 1'!B20/'Exh 1'!B9*365 -> 424.24795 | C16: ='Exh 1'!C20/'Exh 1'!C9*365 -> 432.07556 | D16: ='Exh 1'!D20/'Exh 1'!D9*365 -> 436.46562 | E16: ='Exh 1'!E20/'Exh 1'!E9*365 -> 476.29817 | G16: 386.3
A17: Payable days (AP / Purchases * 365) | B17: ='Exh 1'!B26/'Exh 1'!B33*365 -> 15.553977 | C17: ='Exh 1'!C26/'Exh 1'!C33*365 -> 13.323003 | D17: ='Exh 1'!D26/'Exh 1'!D33*365 -> 10.189206 | E17: ='Exh 1'!E26/'Exh 1'!E33*365 -> 9.8595354 | G17: 26.9
A18: NFA turnover (Revenue / NFA) | B18: ='Exh 1'!B8/'Exh 1'!B23 -> 2.3742849 | C18: ='Exh 1'!C8/'Exh 1'!C23 -> 2.4288722 | D18: ='Exh 1'!D8/'Exh 1'!D23 -> 2.3632579 | E18: ='Exh 1'!E8/'Exh 1'!E23 -> 3.0146594 | G18: 2.7
A20: 1Benchmark figures are based on 2014 financial ratios of publicly traded horticulture producers.
